{
  "type": "Feature",
  "properties": {
    "gn:admin1_code":"05",
    "gn:asciiname":"Tal-Papa",
    "gn:country_code":"MT",
    "gn:dem":44,
    "gn:feature_class":"P",
    "gn:feature_code":"PPL",
    "gn:name":"Tal-Papa",
    "gn:population":0,
    "gn:timezone":"Europe/Malta",
    "iso:country":"MT",
    "wof:name":"Tal-Papa",
    "wof:placetype":"locality"
},
  "geometry": {"coordinates":[14.52278,35.81778],"type":"Point"}
}