{
  "type": "Feature",
  "properties": {
    "gn:admin1_code":"34",
    "gn:asciiname":"In-Nahhalija",
    "gn:country_code":"MT",
    "gn:dem":21,
    "gn:feature_class":"P",
    "gn:feature_code":"PPL",
    "gn:name":"In-Na\u0127\u0127alija",
    "gn:population":0,
    "gn:timezone":"Europe/Malta",
    "iso:country":"MT",
    "name:und_x_variant":[
        "In-nah-Halia",
        "In-Na\u0127\u0127alija"
    ],
    "wof:name":"In-Nahhalija",
    "wof:placetype":"locality"
},
  "geometry": {"coordinates":[14.34278,35.93528],"type":"Point"}
}