{
  "type": "Feature",
  "properties": {
    "gn:admin1_code":"12",
    "gn:asciiname":"Santu Pietru",
    "gn:country_code":"MT",
    "gn:dem":120,
    "gn:feature_class":"P",
    "gn:feature_code":"PPL",
    "gn:name":"Santu Pietru",
    "gn:population":0,
    "gn:timezone":"Europe/Malta",
    "iso:country":"MT",
    "name:und_x_variant":[
        "San Pietru",
        "Santu Pietru"
    ],
    "wof:name":"Santu Pietru",
    "wof:placetype":"locality"
},
  "geometry": {"coordinates":[14.20111,36.06083],"type":"Point"}
}