{
  "type": "Feature",
  "properties": {
    "gn:admin1_code":"52",
    "gn:asciiname":"Wardija Crossroads",
    "gn:country_code":"MT",
    "gn:dem":11,
    "gn:feature_class":"P",
    "gn:feature_code":"PPL",
    "gn:name":"Wardija Crossroads",
    "gn:population":0,
    "gn:timezone":"Europe/Malta",
    "iso:country":"MT",
    "name:und_x_variant":[
        "Wardia Cross Roads",
        "Wardija Crossroads"
    ],
    "wof:name":"Wardija Crossroads",
    "wof:placetype":"locality"
},
  "geometry": {"coordinates":[14.41111,35.93806],"type":"Point"}
}