{
  "type": "Feature",
  "properties": {
    "gn:population":1534,
    "iso:country":"MT",
    "name:ara_x_preferred":[
        "\u0642\u0627\u0644\u0627\u060c \u0645\u0627\u0644\u0637\u0627"
    ],
    "name:baq_x_preferred":[
        "Qala"
    ],
    "name:ben_x_preferred":[
        "\u0995\u09be\u09b2\u09be"
    ],
    "name:cat_x_preferred":[
        "Qala"
    ],
    "name:ceb_x_preferred":[
        "Il-Qala"
    ],
    "name:dan_x_preferred":[
        "Qala"
    ],
    "name:deu_x_preferred":[
        "Qala"
    ],
    "name:dut_x_preferred":[
        "Qala"
    ],
    "name:eng_x_preferred":[
        "Qala"
    ],
    "name:eus_x_preferred":[
        "Qala"
    ],
    "name:fin_x_preferred":[
        "Qala"
    ],
    "name:fra_x_preferred":[
        "Il-Qala"
    ],
    "name:fre_x_preferred":[
        "Qala"
    ],
    "name:ger_x_preferred":[
        "Qala"
    ],
    "name:gre_x_preferred":[
        "\u039a\u03ac\u03bb\u03b1"
    ],
    "name:guj_x_preferred":[
        "\u0a95\u0acd\u0ab5\u0abe\u0ab2\u0abe"
    ],
    "name:hin_x_preferred":[
        "\u0915\u093e\u0932\u093e."
    ],
    "name:hun_x_preferred":[
        "Qala"
    ],
    "name:ind_x_preferred":[
        "Qala"
    ],
    "name:ita_x_preferred":[
        "La Cala"
    ],
    "name:jpn_x_preferred":[
        "\u30a2\u30e9"
    ],
    "name:kan_x_preferred":[
        "\u0c96\u0cb2\u0cbe"
    ],
    "name:kor_x_preferred":[
        "\uc54c\ub77c"
    ],
    "name:lav_x_preferred":[
        "Kala"
    ],
    "name:lit_x_preferred":[
        "Kala"
    ],
    "name:mar_x_preferred":[
        "\u0915\u094d\u092f\u0942\u090f\u0932\u093e"
    ],
    "name:may_x_preferred":[
        "Qala"
    ],
    "name:mlt_x_preferred":[
        "Il-Qala"
    ],
    "name:nld_x_preferred":[
        "Qala"
    ],
    "name:nob_x_preferred":[
        "Qala"
    ],
    "name:pol_x_preferred":[
        "Qala"
    ],
    "name:por_x_preferred":[
        "Qala"
    ],
    "name:rus_x_preferred":[
        "\u041a\u0430\u043b\u0430"
    ],
    "name:scn_x_preferred":[
        "Qala"
    ],
    "name:sin_x_preferred":[
        "\u0d9a\u0dca\u0dc0\u0dcf\u0dbd\u0dcf"
    ],
    "name:spa_x_preferred":[
        "Qala"
    ],
    "name:swe_x_preferred":[
        "Il-Qala"
    ],
    "name:tam_x_preferred":[
        "\u0b95\u0bbf\u0baf\u0bb2\u0bbe"
    ],
    "name:tel_x_preferred":[
        "\u0c16\u0c3e\u0c32\u0c3e"
    ],
    "name:tha_x_preferred":[
        "\u0e01\u0e27\u0e32\u0e25\u0e32"
    ],
    "name:tur_x_preferred":[
        "Qala"
    ],
    "name:ukr_x_preferred":[
        "\u041a\u0430\u043b\u0430"
    ],
    "name:unk_x_variant":[
        "Il-Qala"
    ],
    "name:urd_x_preferred":[
        "\u0622\u0644\u0627\u060c \u0645\u0627\u0644\u0679\u0627"
    ],
    "name:vie_x_preferred":[
        "Qala"
    ],
    "qs:a0":"Malta",
    "qs:a1":"*Ghajnsielem u Kemmuna",
    "qs:a1r":"0",
    "qs:adm0":"Malta",
    "qs:la_lc":"*",
    "qs:level":"locality",
    "qs:loc":"Qala",
    "qs:loc_alt":"Qala",
    "qs:pop":0,
    "qs:type":"buffered point",
    "wd:wordcount":4187,
    "wof:name":"Qala",
    "wof:placetype":"locality",
    "wof:population":1534
},
  "geometry": {"coordinates":[14.293365,36.019612],"type":"Point"}
}