{
  "type": "Feature",
  "properties": {
    "gn:admin1_code":"52",
    "gn:asciiname":"L-Imbordin",
    "gn:country_code":"MT",
    "gn:dem":45,
    "gn:feature_class":"P",
    "gn:feature_code":"PPL",
    "gn:name":"L-Imbordin",
    "gn:population":0,
    "gn:timezone":"Europe/Malta",
    "iso:country":"MT",
    "name:und_x_variant":[
        "Tal-Imbordin",
        "L-Imbordin"
    ],
    "wof:name":"L-Imbordin",
    "wof:placetype":"locality"
},
  "geometry": {"coordinates":[14.37167,35.94333],"type":"Point"}
}