{
  "type": "Feature",
  "properties": {
    "gn:admin1_code":"14",
    "gn:asciiname":"Fanal",
    "gn:country_code":"MT",
    "gn:dem":104,
    "gn:feature_class":"P",
    "gn:feature_code":"PPL",
    "gn:name":"Fanal",
    "gn:population":445,
    "gn:timezone":"Europe/Malta",
    "iso:country":"MT",
    "wof:name":"Fanal",
    "wof:placetype":"locality",
    "wof:population":445
},
  "geometry": {"coordinates":[14.22139,36.06374],"type":"Point"}
}