{
  "type": "Feature",
  "properties": {
    "gn:admin1_code":"43",
    "gn:asciiname":"Tal-Handaq",
    "gn:country_code":"MT",
    "gn:dem":66,
    "gn:feature_class":"P",
    "gn:feature_code":"PPL",
    "gn:name":"Tal-\u0126andaq",
    "gn:population":0,
    "gn:timezone":"Europe/Malta",
    "iso:country":"MT",
    "name:und_x_variant":[
        "Il Handak",
        "Tal Handak",
        "Tal-\u0126andaq"
    ],
    "wof:name":"Tal-Handaq",
    "wof:placetype":"locality"
},
  "geometry": {"coordinates":[14.46806,35.87083],"type":"Point"}
}