{
  "type": "Feature",
  "properties": {
    "gn:admin1_code":"44",
    "gn:asciiname":"Ta' San Niklaw",
    "gn:country_code":"MT",
    "gn:dem":130,
    "gn:feature_class":"P",
    "gn:feature_code":"PPL",
    "gn:name":"Ta\u2019 San Niklaw",
    "gn:population":0,
    "gn:timezone":"Europe/Malta",
    "iso:country":"MT",
    "name:und_x_variant":[
        "Ta San Niclau",
        "Ta\u2019 San Niklaw"
    ],
    "wof:name":"Ta' San Niklaw",
    "wof:placetype":"locality"
},
  "geometry": {"coordinates":[14.44167,35.83556],"type":"Point"}
}