{
  "type": "Feature",
  "properties": {
    "gn:admin1_code":"64",
    "gn:asciiname":"San Leonardo",
    "gn:country_code":"MT",
    "gn:dem":59,
    "gn:feature_class":"P",
    "gn:feature_code":"PPL",
    "gn:name":"San Leonardo",
    "gn:population":0,
    "gn:timezone":"Europe/Malta",
    "iso:country":"MT",
    "name:ceb_x_preferred":[
        "San Leonardo"
    ],
    "name:deu_x_preferred":[
        "San Leonardo"
    ],
    "name:epo_x_preferred":[
        "San Leonardo"
    ],
    "name:fra_x_preferred":[
        "San Leonardo"
    ],
    "name:hun_x_preferred":[
        "San Leonardo"
    ],
    "name:ita_x_preferred":[
        "San Leonardo"
    ],
    "name:nld_x_preferred":[
        "San Leonardo"
    ],
    "name:spa_x_preferred":[
        "San Leonardo"
    ],
    "name:srp_x_preferred":[
        "\u0421\u0430\u043d \u041b\u0435\u043e\u043d\u0430\u0440\u0434\u043e"
    ],
    "name:swe_x_preferred":[
        "San Leonardo"
    ],
    "name:und_x_variant":[
        "San Annard",
        "San Leonardo"
    ],
    "name:war_x_preferred":[
        "San Leonardo"
    ],
    "wof:name":"San Leonardo",
    "wof:placetype":"locality"
},
  "geometry": {"coordinates":[14.55583,35.87833],"type":"Point"}
}