{
  "type": "Feature",
  "properties": {
    "gn:admin1_code":"64",
    "gn:asciiname":"San Leonardo",
    "gn:country_code":"MT",
    "gn:dem":59,
    "gn:feature_class":"P",
    "gn:feature_code":"PPL",
    "gn:name":"San Leonardo",
    "gn:population":0,
    "gn:timezone":"Europe/Malta",
    "iso:country":"MT",
    "name:und_x_variant":[
        "San Annard",
        "San Leonardo"
    ],
    "wof:name":"San Leonardo",
    "wof:placetype":"locality"
},
  "geometry": {"coordinates":[14.55583,35.87833],"type":"Point"}
}