{
  "type": "Feature",
  "properties": {
    "gn:country":"MT",
    "gn:fcode":"PPL",
    "gn:population":0,
    "iso:country":"MT",
    "name:und_x_variant":[
        "Tal Baiada"
    ],
    "qs_pg:aaroncc":"MT",
    "qs_pg:gn_country":"MT",
    "qs_pg:gn_fcode":"PPL",
    "qs_pg:gn_pop":0,
    "qs_pg:name":"Tal-Bajjada",
    "qs_pg:name_adm0":"Malta",
    "qs_pg:name_adm1":"Malta Majjistral",
    "qs_pg:photos":481,
    "qs_pg:photos_1k":97,
    "qs_pg:photos_9k":2,
    "qs_pg:photos_9r":5,
    "qs_pg:photos_all":481,
    "qs_pg:photos_sr":7,
    "qs_pg:pop_sr":0,
    "qs_pg:qs_pg_placetype":"locality",
    "qs_pg:qs_pg_placetype_gp":"Town",
    "qs_pg:woe_adm0":23424897,
    "woe:adm0_id":23424897,
    "woe:name_adm0":"Malta",
    "woe:name_adm1":"Malta Majjistral",
    "woe:placetype":"Town",
    "wof:name":"Tal-Bajjada",
    "wof:placetype":"locality"
},
  "geometry": {"coordinates":[14.42556,35.83722],"type":"Point"}
}