{
  "type": "Feature",
  "properties": {
    "gn:admin1_code":"34",
    "gn:asciiname":"Ghajn Zejtuna",
    "gn:country_code":"MT",
    "gn:dem":21,
    "gn:feature_class":"P",
    "gn:feature_code":"PPL",
    "gn:name":"G\u0127ajn \u017bejtuna",
    "gn:population":0,
    "gn:timezone":"Europe/Malta",
    "iso:country":"MT",
    "name:und_x_variant":[
        "Ghain Zeituna",
        "G\u0127ajn \u017bejtuna"
    ],
    "wof:name":"Ghajn Zejtuna",
    "wof:placetype":"locality"
},
  "geometry": {"coordinates":[14.36722,35.96639000000001],"type":"Point"}
}