{
  "type": "Feature",
  "properties": {
    "gn:admin1_code":"44",
    "gn:asciiname":"Tal-Kittienija",
    "gn:country_code":"MT",
    "gn:dem":96,
    "gn:feature_class":"P",
    "gn:feature_code":"PPL",
    "gn:name":"Tal-Kittienija",
    "gn:population":0,
    "gn:timezone":"Europe/Malta",
    "iso:country":"MT",
    "name:und_x_variant":[
        "Tal Chittienija",
        "Tal-Kittienija"
    ],
    "wof:name":"Tal-Kittienija",
    "wof:placetype":"locality"
},
  "geometry": {"coordinates":[14.46833,35.83694000000001],"type":"Point"}
}