{
  "type": "Feature",
  "properties": {
    "gn:gn_country":"MT",
    "gn:gn_fcode":"PPL",
    "gn:gn_pop":10,
    "gn:population":10,
    "iso:country":"MT",
    "name:ara_x_preferred":[
        "\u0643\u0645\u0648\u0646\u0629"
    ],
    "name:bel_x_preferred":[
        "\u041a\u0430\u043c\u0456\u043d\u0430"
    ],
    "name:cat_x_preferred":[
        "Comino"
    ],
    "name:ceb_x_preferred":[
        "Kemmuna"
    ],
    "name:ces_x_preferred":[
        "Comino"
    ],
    "name:dan_x_preferred":[
        "Comino"
    ],
    "name:deu_x_preferred":[
        "Comino"
    ],
    "name:eng_x_historical":[
        "Ephaestia"
    ],
    "name:eng_x_preferred":[
        "Comino"
    ],
    "name:eng_x_variant":[
        "Ephaestia"
    ],
    "name:epo_x_preferred":[
        "Comino"
    ],
    "name:eus_x_preferred":[
        "Comino"
    ],
    "name:fin_x_preferred":[
        "Kemmuna"
    ],
    "name:fra_x_preferred":[
        "Comino"
    ],
    "name:gle_x_preferred":[
        "Kemmuna"
    ],
    "name:heb_x_preferred":[
        "\u05e7\u05d5\u05de\u05d9\u05e0\u05d5"
    ],
    "name:hrv_x_preferred":[
        "Comino"
    ],
    "name:hun_x_preferred":[
        "Comino"
    ],
    "name:ita_x_preferred":[
        "Comino"
    ],
    "name:jpn_x_preferred":[
        "\u30b3\u30df\u30ce\u5cf6"
    ],
    "name:kor_x_preferred":[
        "\ucf54\ubbf8\ub178\uc12c"
    ],
    "name:lat_x_preferred":[
        "Hephaestia"
    ],
    "name:lim_x_preferred":[
        "Comino"
    ],
    "name:lit_x_preferred":[
        "Kominas"
    ],
    "name:ltz_x_preferred":[
        "Comino"
    ],
    "name:mkd_x_preferred":[
        "\u041a\u043e\u043c\u0438\u043d\u043e"
    ],
    "name:mlt_x_preferred":[
        "Kemmuna"
    ],
    "name:nld_x_preferred":[
        "Comino"
    ],
    "name:nno_x_preferred":[
        "Comino"
    ],
    "name:nor_x_preferred":[
        "Comino"
    ],
    "name:pol_x_preferred":[
        "Comino"
    ],
    "name:por_x_preferred":[
        "Comino"
    ],
    "name:ron_x_preferred":[
        "Insula Comino"
    ],
    "name:rus_x_preferred":[
        "\u041a\u043e\u043c\u0438\u043d\u043e"
    ],
    "name:scn_x_preferred":[
        "Cumminu"
    ],
    "name:sco_x_preferred":[
        "Comino"
    ],
    "name:slk_x_preferred":[
        "Comino"
    ],
    "name:spa_x_preferred":[
        "Comino"
    ],
    "name:srp_x_preferred":[
        "\u041a\u043e\u043c\u0438\u043d\u043e"
    ],
    "name:swe_x_preferred":[
        "Comino"
    ],
    "name:szl_x_preferred":[
        "Comino"
    ],
    "name:ukr_x_preferred":[
        "\u041a\u043e\u043c\u0456\u043d\u043e"
    ],
    "name:zho_x_preferred":[
        "\u79d1\u7c73\u8bfa\u5c9b"
    ],
    "qs_pg:aaroncc":"MT",
    "qs_pg:gn_country":"MT",
    "qs_pg:gn_fcode":"PPL",
    "qs_pg:gn_pop":10,
    "qs_pg:name":"Comino",
    "qs_pg:photos_9r":0,
    "qs_pg:photos_sr":0,
    "qs_pg:pop_sr":1,
    "qs_pg:qs_pg_placetype":"locality",
    "wof:name":"Comino",
    "wof:placetype":"locality",
    "wof:population":10
},
  "geometry": {"coordinates":[14.3393,36.01231],"type":"Point"}
}