{
  "type": "Feature",
  "properties": {
    "gn:gn_country":"MT",
    "gn:gn_fcode":"PPL",
    "gn:gn_pop":10,
    "gn:population":10,
    "iso:country":"MT",
    "name:eng_x_historical":[
        "Ephaestia"
    ],
    "name:eng_x_preferred":[
        "Comino"
    ],
    "name:eng_x_variant":[
        "Ephaestia"
    ],
    "name:mlt_x_preferred":[
        "Kemmuna"
    ],
    "name:rus_x_preferred":[
        "\u041a\u043e\u043c\u0438\u043d\u043e"
    ],
    "qs_pg:aaroncc":"MT",
    "qs_pg:gn_country":"MT",
    "qs_pg:gn_fcode":"PPL",
    "qs_pg:gn_pop":10,
    "qs_pg:name":"Comino",
    "qs_pg:photos_9r":0,
    "qs_pg:photos_sr":0,
    "qs_pg:pop_sr":1,
    "qs_pg:qs_pg_placetype":"locality",
    "wof:name":"Comino",
    "wof:placetype":"locality",
    "wof:population":10
},
  "geometry": {"coordinates":[14.3393,36.01231],"type":"Point"}
}