{
  "type": "Feature",
  "properties": {
    "gn:admin1_code":"16",
    "gn:asciiname":"Ix-Xlejli",
    "gn:country_code":"MT",
    "gn:dem":77,
    "gn:feature_class":"P",
    "gn:feature_code":"PPL",
    "gn:name":"Ix-Xlejli",
    "gn:population":0,
    "gn:timezone":"Europe/Malta",
    "iso:country":"MT",
    "name:und_x_variant":[
        "Ta Xlejli",
        "Ix-Xlejli"
    ],
    "wof:name":"Ix-Xlejli",
    "wof:placetype":"locality"
},
  "geometry": {"coordinates":[14.50722,35.85111],"type":"Point"}
}